{
  "$schema": "../../node_modules/ng-packagr/ng-package.schema.json",
  "dest": "../../dist/starter",
  "assets": [],
  "lib": {
    "entryFile": "src/public-api.ts",
    "umdId": "ng.lamnhan.nguix.starter",
    "umdModuleIds": {
      "@lamnhan/ngx-useful": "ng.lamnhan.useful",
      "@lamnhan/ngx-schemata": "ng.lamnhan.schemata",
      "@ngneat/transloco": "ng.transloco",
      "ngx-markdown": "ngxMarkdown",
      "croppie": "croppie",
      "compressorjs": "compressorjs",
      "basiclightbox": "basiclightbox"
    }
  },
  "allowedNonPeerDependencies": [
    "ngx-markdown",
    "croppie",
    "compressorjs",
    "basiclightbox"
  ]
}
